timewarp/__init__.py
timewarp/bindings.py
timewarp/cli.py
timewarp/codec.py
timewarp/determinism.py
timewarp/diff.py
timewarp/events.py
timewarp/interactive_debug.py
timewarp/memory.py
timewarp/pruners.py
timewarp/py.typed
timewarp/store.py
timewarp/telemetry.py
timewarp/cli/__init__.py
timewarp/cli/main.py
timewarp/cli/commands/debug.py
timewarp/cli/commands/diff.py
timewarp/cli/commands/dspy.py
timewarp/cli/commands/events.py
timewarp/cli/commands/export.py
timewarp/cli/commands/fsck.py
timewarp/cli/commands/inject.py
timewarp/cli/commands/list_runs.py
timewarp/cli/commands/memory.py
timewarp/cli/commands/resume.py
timewarp/cli/commands/tools.py
timewarp/cli/helpers/blobs.py
timewarp/cli/helpers/events.py
timewarp/cli/helpers/filters.py
timewarp/cli/helpers/imports.py
timewarp/cli/helpers/jsonio.py
timewarp/cli/helpers/prompts.py
timewarp/cli/helpers/state.py
timewarp/exporters/dspy.py
timewarp/exporters/langsmith.py
timewarp/langgraph/__init__.py
timewarp/langgraph/anchors.py
timewarp/langgraph/batch.py
timewarp/langgraph/classify.py
timewarp/langgraph/hashing.py
timewarp/langgraph/memory.py
timewarp/langgraph/messages.py
timewarp/langgraph/recorder.py
timewarp/langgraph/retrieval.py
timewarp/langgraph/serialize.py
timewarp/langgraph/stream_async.py
timewarp/langgraph/stream_sync.py
timewarp/langgraph/taps.py
timewarp/langgraph/versioning.py
timewarp/replay/__init__.py
timewarp/replay/exceptions.py
timewarp/replay/langgraph.py
timewarp/replay/no_network.py
timewarp/replay/session.py
timewarp/replay/wrappers.py
timewarp/utils/diffing.py
timewarp/utils/fingerprint.py
timewarp/utils/hashing.py
timewarp/utils/json.py
timewarp/utils/logging.py
timewarp_llm-0.2.1.dist-info/licenses/LICENSE
timewarp_llm-0.2.1.dist-info/METADATA
timewarp_llm-0.2.1.dist-info/WHEEL
timewarp_llm-0.2.1.dist-info/entry_points.txt
timewarp_llm-0.2.1.dist-info/top_level.txt
timewarp_llm-0.2.1.dist-info/RECORD
