Metadata-Version: 2.4
Name: timewarp-llm
Version: 0.2.1
Summary: Event-sourced recording + deterministic replay + time‑travel debugger for LLM agents.
Author: Timewarp maintainers
License-Expression: Apache-2.0
Project-URL: Homepage, https://github.com/aleks-apostle/timewarp
Project-URL: Repository, https://github.com/aleks-apostle/timewarp
Project-URL: Issues, https://github.com/aleks-apostle/timewarp/issues
Project-URL: Changelog, https://github.com/aleks-apostle/timewarp/releases
Keywords: LLM,LangGraph,LangChain,event-sourcing,replay,debugger,OpenTelemetry,CLI,determinism
Classifier: Programming Language :: Python :: 3 :: Only
Classifier: Programming Language :: Python :: 3.11
Classifier: Programming Language :: Python :: 3.12
Classifier: Operating System :: OS Independent
Classifier: Intended Audience :: Developers
Classifier: Environment :: Console
Classifier: Topic :: Software Development :: Debuggers
Classifier: Typing :: Typed
Requires-Python: >=3.11
License-File: LICENSE
Requires-Dist: pydantic>=2.6
Requires-Dist: orjson>=3.10
Requires-Dist: zstandard>=0.23
Requires-Dist: deepdiff>=8.0
Requires-Dist: rich>=13.7
Provides-Extra: otel
Requires-Dist: opentelemetry-api>=1.25; extra == "otel"
Requires-Dist: opentelemetry-sdk>=1.25; extra == "otel"
Provides-Extra: dev
Requires-Dist: ruff>=0.6; extra == "dev"
Requires-Dist: mypy>=1.10; extra == "dev"
Requires-Dist: pytest>=8.3; extra == "dev"
Requires-Dist: langgraph>=0.6; extra == "dev"
Requires-Dist: langchain-core>=0.3; extra == "dev"
Provides-Extra: examples
Requires-Dist: langgraph>=0.6; python_version >= "3.10" and extra == "examples"
Requires-Dist: langchain-core>=0.3; python_version >= "3.10" and extra == "examples"
Provides-Extra: mcp
Requires-Dist: langchain-mcp-adapters>=0.1; python_version >= "3.10" and extra == "mcp"
Provides-Extra: dspy
Requires-Dist: dspy>=2.4; extra == "dspy"
Dynamic: license-file
